flowMC/Sampler.py
flowMC/__init__.py
flowMC/resource/__init__.py
flowMC/resource/base.py
flowMC/resource/buffers.py
flowMC/resource/logPDF.py
flowMC/resource/optimizer.py
flowMC/resource/states.py
flowMC/resource/local_kernel/Gaussian_random_walk.py
flowMC/resource/local_kernel/HMC.py
flowMC/resource/local_kernel/MALA.py
flowMC/resource/local_kernel/__init__.py
flowMC/resource/local_kernel/base.py
flowMC/resource/nf_model/NF_proposal.py
flowMC/resource/nf_model/__init__.py
flowMC/resource/nf_model/base.py
flowMC/resource/nf_model/common.py
flowMC/resource/nf_model/realNVP.py
flowMC/resource/nf_model/rqSpline.py
flowMC/resource_strategy_bundle/RQSpline_MALA.py
flowMC/resource_strategy_bundle/RQSpline_MALA_PT.py
flowMC/resource_strategy_bundle/__init__.py
flowMC/resource_strategy_bundle/base.py
flowMC/strategy/__init__.py
flowMC/strategy/base.py
flowMC/strategy/importance_sampling.py
flowMC/strategy/lambda_function.py
flowMC/strategy/optimization.py
flowMC/strategy/parallel_tempering.py
flowMC/strategy/take_steps.py
flowMC/strategy/train_model.py
flowMC/strategy/update_state.py
flowmc-0.4.5.dist-info/METADATA
flowmc-0.4.5.dist-info/WHEEL
flowmc-0.4.5.dist-info/licenses/LICENSE
flowmc-0.4.5.dist-info/RECORD
