Metadata-Version: 2.4
Name: flowMC
Version: 0.4.5
Summary: Normalizing flow exhanced sampler in jax
Project-URL: Documentation, https://github.com/kazewong/flowMC
Author: Marylou Gabrié, Dan Foreman-Mackey
Author-email: Kaze Wong <kazewong.physics@gmail.com>
License: MIT License
License-File: LICENSE
Keywords: autodiff,inference,jax,machine learning,normalizing,sampling
Classifier: Intended Audience :: Science/Research
Classifier: License :: OSI Approved :: MIT License
Classifier: Programming Language :: Python :: 3.11
Classifier: Programming Language :: Python :: 3.12
Classifier: Programming Language :: Python :: 3.13
Classifier: Topic :: Scientific/Engineering :: Artificial Intelligence
Classifier: Topic :: Scientific/Engineering :: Information Analysis
Classifier: Topic :: Scientific/Engineering :: Mathematics
Requires-Python: >=3.11
Requires-Dist: chex>=0.1.87
Requires-Dist: equinox>=0.11.9
Requires-Dist: jax[cpu]>=0.5.0
Requires-Dist: jaxtyping>=0.2.36
Requires-Dist: optax>=0.2.4
Requires-Dist: scikit-learn>=1.6.0
Requires-Dist: tqdm>=4.67.1
Provides-Extra: codeqa
Requires-Dist: coveralls>=4.0.1; extra == 'codeqa'
Requires-Dist: pre-commit>=4.0.1; extra == 'codeqa'
Requires-Dist: pyright>=1.1.389; extra == 'codeqa'
Requires-Dist: pytest>=8.3.3; extra == 'codeqa'
Requires-Dist: ruff>=0.8.0; extra == 'codeqa'
Provides-Extra: cuda
Requires-Dist: jax[cuda12]>=0.5.0; extra == 'cuda'
Provides-Extra: docs
Requires-Dist: mkdocs-gen-files==0.5.0; extra == 'docs'
Requires-Dist: mkdocs-jupyter==0.25.1; extra == 'docs'
Requires-Dist: mkdocs-literate-nav==0.6.1; extra == 'docs'
Requires-Dist: mkdocs-material==9.5.47; extra == 'docs'
Requires-Dist: mkdocs==1.6.1; extra == 'docs'
Requires-Dist: mkdocstrings[python]==0.27.0; extra == 'docs'
Requires-Dist: pymdown-extensions==10.12; extra == 'docs'
Provides-Extra: visualize
Requires-Dist: arviz>=0.21.0; extra == 'visualize'
Requires-Dist: corner>=2.2.3; extra == 'visualize'
Requires-Dist: matplotlib>=3.9.3; extra == 'visualize'
